{
  "type": "C1",
  "nickname": "이성 최우선형",
  "section": "성향 상세 해석",
  "summary": "감정보다 논리를 우선시하는 이성 최우선형은, 상황을 객관적으로 바라보며 문제를 빠르게 해결하려는 성향입니다.",
  "content": [
    {
      "title": "감정 처리 방식",
      "description": "감정보다 상황을 먼저 분석하고, 감정에 휘둘리지 않으려는 태도가 강합니다. 감정을 느끼지 않는 것은 아니지만, 그것을 우선적으로 다루기보단 이성적인 해결책을 찾는 데 집중합니다."
    },
    {
      "title": "대인관계에서의 특징",
      "description": "관계에서 감정보다 논리와 효율을 중시하며, 감정적 호소보다 현실적인 대화를 선호합니다. 그로 인해 상대방이 ‘차갑다’고 느낄 수 있으나, 명확하고 일관된 태도는 신뢰감을 주기도 합니다."
    },
    {
      "title": "감정 피로의 양상",
      "description": "감정을 억누르고 합리화하려는 경향이 있어, 피로가 누적되어도 인식하지 못할 수 있습니다. 이로 인해 내면에 감정이 쌓이고, 때때로 예기치 못한 순간에 터져나올 수 있어요."
    },
    {
      "title": "의사소통에서의 패턴",
      "description": "말을 할 때는 핵심만 간결하게 전달하고, 감정적 표현은 최소화하려 합니다. 공감보다는 해결책을 제시하려는 경향이 강해, 감정적 위로가 필요한 상황에서는 다소 거리감이 느껴질 수 있습니다."
    }
  ],
  "note": "감정보다 논리를 앞세우는 당신의 성향은 문제 해결에 강점이 있지만, 때로는 '공감'이라는 감정의 언어가 더 큰 해결책이 될 수 있습니다. 당신의 이성과 감정, 두 축 모두를 존중해 주세요."
}
